[
  {
    "anonymous": false,
    "inputs": [
      {
        "indexed": true,
        "internalType": "bytes",
        "name": "b",
        "type": "bytes"
      },
      {
        "indexed": false,
        "internalType": "bytes",
        "name": "c",
        "type": "bytes"
      }
    ],
    "name": "BytesEvent",
    "type": "event"
  },
  {
    "anonymous": false,
    "inputs": [
      {
        "indexed": true,
        "internalType": "uint256[1]",
        "name": "u",
        "type": "uint256[1]"
      },
      {
        "indexed": false,
        "internalType": "uint256[1]",
        "name": "v",
        "type": "uint256[1]"
      }
    ],
    "name": "FixedArrayEvent1",
    "type": "event"
  },
  {
    "anonymous": false,
    "inputs": [
      {
        "indexed": true,
        "internalType": "uint256[2]",
        "name": "u",
        "type": "uint256[2]"
      },
      {
        "indexed": false,
        "internalType": "uint256[2]",
        "name": "v",
        "type": "uint256[2]"
      }
    ],
    "name": "FixedArrayEvent2",
    "type": "event"
  },
  {
    "anonymous": false,
    "inputs": [
      {
        "indexed": true,
        "internalType": "bytes11",
        "name": "b",
        "type": "bytes11"
      },
      {
        "indexed": false,
        "internalType": "bytes11",
        "name": "c",
        "type": "bytes11"
      }
    ],
    "name": "FixedBytesEvent",
    "type": "event"
  },
  {
    "anonymous": false,
    "inputs": [
      {
        "indexed": true,
        "internalType": "string",
        "name": "s",
        "type": "string"
      },
      {
        "indexed": false,
        "internalType": "string",
        "name": "u",
        "type": "string"
      }
    ],
    "name": "StringEvent",
    "type": "event"
  },
  {
    "anonymous": false,
    "inputs": [
      {
        "indexed": true,
        "internalType": "uint256[]",
        "name": "u",
        "type": "uint256[]"
      },
      {
        "indexed": false,
        "internalType": "uint256[]",
        "name": "v",
        "type": "uint256[]"
      }
    ],
    "name": "VarLenArrayEvent1",
    "type": "event"
  },
  {
    "inputs": [],
    "name": "emitBytesEvent",
    "outputs": [],
    "stateMutability": "nonpayable",
    "type": "function"
  },
  {
    "inputs": [],
    "name": "emitFixedArrayEvent1",
    "outputs": [],
    "stateMutability": "nonpayable",
    "type": "function"
  },
  {
    "inputs": [],
    "name": "emitFixedArrayEvent2",
    "outputs": [],
    "stateMutability": "nonpayable",
    "type": "function"
  },
  {
    "inputs": [],
    "name": "emitFixedBytesEvent",
    "outputs": [],
    "stateMutability": "nonpayable",
    "type": "function"
  },
  {
    "inputs": [],
    "name": "emitStringEvent",
    "outputs": [],
    "stateMutability": "nonpayable",
    "type": "function"
  },
  {
    "inputs": [],
    "name": "emitVarLenArrayEvent1",
    "outputs": [],
    "stateMutability": "nonpayable",
    "type": "function"
  },
  {
    "inputs": [],
    "name": "emitVarLenArrayEvent2",
    "outputs": [],
    "stateMutability": "nonpayable",
    "type": "function"
  }
]
